aiverify_partial_dependence_plot/__init__.py
aiverify_partial_dependence_plot/__main__.py
aiverify_partial_dependence_plot/algo.meta.json
aiverify_partial_dependence_plot/algo.py
aiverify_partial_dependence_plot/algo_init.py
aiverify_partial_dependence_plot/input.schema.json
aiverify_partial_dependence_plot/output.schema.json
aiverify_partial_dependence_plot/plugin_init.py
aiverify_partial_dependence_plot-2.1.0.dist-info/METADATA
aiverify_partial_dependence_plot-2.1.0.dist-info/WHEEL
aiverify_partial_dependence_plot-2.1.0.dist-info/entry_points.txt
aiverify_partial_dependence_plot-2.1.0.dist-info/licenses/AUTHORS.rst
aiverify_partial_dependence_plot-2.1.0.dist-info/licenses/LICENSE
aiverify_partial_dependence_plot-2.1.0.dist-info/licenses/NOTICE.md
aiverify_partial_dependence_plot-2.1.0.dist-info/RECORD
