Metadata-Version: 2.4
Name: aiverify-partial-dependence-plot
Version: 2.1.0
Summary: AI Verify implementation of Partial Dependence Plot (PDP) that explains how each feature and its feature value contribute to the predictions.
Author: AI Verify
License-File: AUTHORS.rst
License-File: LICENSE
License-File: NOTICE.md
Requires-Python: <3.13,>=3.10
Requires-Dist: aiverify-test-engine>=2.1.0
Requires-Dist: numpy==1.26.4
Requires-Dist: scipy==1.14.1
